biometrica_pb2.py
biometrica_pb2_grpc.py
bmauth_client.py
bmpython-0.111.data/scripts/bmpython
bmpython-0.111.dist-info/METADATA
bmpython-0.111.dist-info/WHEEL
bmpython-0.111.dist-info/top_level.txt
bmpython-0.111.dist-info/RECORD
